netsmith-0.1.1.dist-info/METADATA
netsmith-0.1.1.dist-info/WHEEL
netsmith-0.1.1.dist-info/entry_points.txt
netsmith-0.1.1.dist-info/licenses/LICENSE
netsmith_rs/__init__.py
netsmith_rs/netsmith_rs.cpython-312-x86_64-linux-gnu.so
netsmith-0.1.1.dist-info/RECORD
