Metadata-Version: 2.4
Name: netsmith
Version: 0.1.1
Classifier: Programming Language :: Python :: 3
Classifier: Programming Language :: Python :: 3.12
Classifier: Programming Language :: Python :: 3.13
Classifier: License :: OSI Approved :: MIT License
Classifier: Operating System :: OS Independent
Classifier: Topic :: Scientific/Engineering
Classifier: Topic :: Scientific/Engineering :: Information Analysis
Classifier: Intended Audience :: Science/Research
Requires-Dist: numpy>=1.23,<3.0.0
Requires-Dist: pytest>=7.0 ; extra == 'dev'
Requires-Dist: pytest-cov>=4.0 ; extra == 'dev'
Requires-Dist: black>=23.0 ; extra == 'dev'
Requires-Dist: flake8>=6.0 ; extra == 'dev'
Requires-Dist: mypy>=1.0 ; extra == 'dev'
Requires-Dist: isort>=5.12 ; extra == 'dev'
Requires-Dist: networkx>=3.0,<4.0.0 ; extra == 'networkx'
Requires-Dist: pandas>=1.5,<3.0.0 ; extra == 'pandas'
Requires-Dist: polars>=0.20,<1.0.0 ; extra == 'polars'
Requires-Dist: scipy>=1.9,<2.0.0 ; extra == 'scipy'
Provides-Extra: dev
Provides-Extra: networkx
Provides-Extra: pandas
Provides-Extra: polars
Provides-Extra: rust
Provides-Extra: scipy
License-File: LICENSE
Summary: Fast network analysis library with Rust acceleration
Author-email: "Kyle T. Jones" <kyle@kyletjones.com>
Requires-Python: >=3.12
